turingpoint/__init__.py
turingpoint/assembly.py
turingpoint/definitions.py
turingpoint/gymnasium_utils.py
turingpoint/mcts.py
turingpoint/pandas_utils.py
turingpoint/pz_utils.py
turingpoint/sb3_utils.py
turingpoint/self_play.py
turingpoint/tensorboard_utils.py
turingpoint/torch_utils.py
turingpoint/utils.py
turingpoint-0.2.2.dist-info/METADATA
turingpoint-0.2.2.dist-info/WHEEL
turingpoint-0.2.2.dist-info/top_level.txt
turingpoint-0.2.2.dist-info/zip-safe
turingpoint-0.2.2.dist-info/RECORD
