Metadata-Version: 2.4
Name: turingpoint
Version: 0.2.2
Summary: Reinforcement Learning (RL) library
Home-page: https://github.com/zbenmo/turingpoint
Author: Oren Zeev-Ben-Mordehai
Author-email: zbenmo@gmail.com
Keywords: Reinforcement Learning,Framework,Integration
Classifier: Intended Audience :: Developers
Classifier: Intended Audience :: Science/Research
Classifier: Programming Language :: Python :: 3
Classifier: Programming Language :: Python :: 3.7
Classifier: Programming Language :: Python :: 3.8
Classifier: Programming Language :: Python :: 3.9
Classifier: License :: OSI Approved :: MIT License
Classifier: Topic :: Scientific/Engineering
Classifier: Topic :: Scientific/Engineering :: Artificial Intelligence
Requires-Dist: tqdm
Provides-Extra: examples-sb3
Requires-Dist: gymnasium>=0.28.1; extra == "examples-sb3"
Requires-Dist: stable-baselines3[extra]<2.1,>=2.0.0a5; extra == "examples-sb3"
Requires-Dist: pettingzoo[batterfly,classic]<1.23,>=1.22.3; extra == "examples-sb3"
Requires-Dist: pymunk; extra == "examples-sb3"
Requires-Dist: tianshou<0.6,>=0.5.0; extra == "examples-sb3"
Requires-Dist: numpy; extra == "examples-sb3"
Provides-Extra: examples-torch
Requires-Dist: gymnasium[accept-rom-licesnse,atari,box2d]; extra == "examples-torch"
Requires-Dist: ale-py; extra == "examples-torch"
Requires-Dist: numpy; extra == "examples-torch"
Provides-Extra: examples-mujoco
Requires-Dist: gymnasium[mujoco]; extra == "examples-mujoco"
Requires-Dist: gymnasium[other]; extra == "examples-mujoco"
Requires-Dist: optuna; extra == "examples-mujoco"
Provides-Extra: optuna
Requires-Dist: plotly; extra == "optuna"
Requires-Dist: optuna; extra == "optuna"
Requires-Dist: optuna-dashboard; extra == "optuna"
